[
  {
    "py/object": "model.address.Address",
    "first_name": "",
    "middle_name": "",
    "last_name": "",
    "nickname": "",
    "title": "",
    "company": "",
    "address": "",
    "home_telephone": "",
    "mobile_telephone": "",
    "work_telephone": "",
    "fax": "",
    "email": "",
    "email2": "",
    "email3": "",
    "homepage": "",
    "birth_day": "",
    "birth_month": "-",
    "birth_year": "",
    "anni_day": "",
    "anni_month": "-",
    "anni_year": "",
    "second_address": "",
    "phone2": "",
    "notes": "",
    "all_phones_from_home_page": null,
    "all_emails_from_home_page": null,
    "id": null
  },
  {
    "py/object": "model.address.Address",
    "first_name": "fnameZgH",
    "middle_name": "mnameOKYj",
    "last_name": "lnamebjJ3",
    "nickname": "nickAw",
    "title": "titleNh",
    "company": "compr",
    "address": "addr",
    "home_telephone": "htel",
    "mobile_telephone": "mtelUMl",
    "work_telephone": "wtelyRy",
    "fax": "fax",
    "email": "email@",
    "email2": "email2@l67",
    "email3": "email3@",
    "homepage": "hpageO5P",
    "birth_day": "",
    "birth_month": "-",
    "birth_year": "",
    "anni_day": "",
    "anni_month": "-",
    "anni_year": "",
    "second_address": "addr2EAi",
    "phone2": "phone2dl",
    "notes": "notes",
    "all_phones_from_home_page": null,
    "all_emails_from_home_page": null,
    "id": null
  },
  {
    "py/object": "model.address.Address",
    "first_name": "fname7xZEEpDal",
    "middle_name": "mnameXns",
    "last_name": "lnameiF",
    "nickname": "nick",
    "title": "titlecytK",
    "company": "compz9Kc",
    "address": "addr2Sf8VM2K",
    "home_telephone": "htelkx4",
    "mobile_telephone": "mtella",
    "work_telephone": "wtel",
    "fax": "faxq",
    "email": "email@vto",
    "email2": "email2@n",
    "email3": "email3@",
    "homepage": "hpageDwJ",
    "birth_day": "",
    "birth_month": "-",
    "birth_year": "",
    "anni_day": "",
    "anni_month": "-",
    "anni_year": "",
    "second_address": "addr2d",
    "phone2": "phone2",
    "notes": "notes0a",
    "all_phones_from_home_page": null,
    "all_emails_from_home_page": null,
    "id": null
  },
  {
    "py/object": "model.address.Address",
    "first_name": "fnameLbEM0e59",
    "middle_name": "mnameO",
    "last_name": "lnameEVm",
    "nickname": "nick5KHC",
    "title": "titlet",
    "company": "compN",
    "address": "addrxAiFL7",
    "home_telephone": "htelNx",
    "mobile_telephone": "mtel",
    "work_telephone": "wtelr",
    "fax": "fax",
    "email": "email@v",
    "email2": "email2@HR",
    "email3": "email3@z",
    "homepage": "hpagetq5",
    "birth_day": "",
    "birth_month": "-",
    "birth_year": "",
    "anni_day": "",
    "anni_month": "-",
    "anni_year": "",
    "second_address": "addr2Oa",
    "phone2": "phone2GVd",
    "notes": "notesHyouCH",
    "all_phones_from_home_page": null,
    "all_emails_from_home_page": null,
    "id": null
  },
  {
    "py/object": "model.address.Address",
    "first_name": "fnamejyI7x4W",
    "middle_name": "mname",
    "last_name": "lnameDGIF6qY",
    "nickname": "nickRlx",
    "title": "titlelkPP",
    "company": "comp5c",
    "address": "addr",
    "home_telephone": "htelsbc",
    "mobile_telephone": "mtelIe",
    "work_telephone": "wtel",
    "fax": "faxS",
    "email": "email@",
    "email2": "email2@Y11v",
    "email3": "email3@Vk6",
    "homepage": "hpage1kq",
    "birth_day": "",
    "birth_month": "-",
    "birth_year": "",
    "anni_day": "",
    "anni_month": "-",
    "anni_year": "",
    "second_address": "addr2YxSc",
    "phone2": "phone26h",
    "notes": "notesqO",
    "all_phones_from_home_page": null,
    "all_emails_from_home_page": null,
    "id": null
  },
  {
    "py/object": "model.address.Address",
    "first_name": "fname",
    "middle_name": "mnamerlAYsIa",
    "last_name": "lnameSoY8g4yFv",
    "nickname": "nick0Yi1",
    "title": "titler",
    "company": "comp",
    "address": "addr",
    "home_telephone": "htelU6G",
    "mobile_telephone": "mtel3e8",
    "work_telephone": "wtelkkK",
    "fax": "fax",
    "email": "email@tO",
    "email2": "email2@GIxy",
    "email3": "email3@g24X",
    "homepage": "hpage",
    "birth_day": "",
    "birth_month": "-",
    "birth_year": "",
    "anni_day": "",
    "anni_month": "-",
    "anni_year": "",
    "second_address": "addr2KkQ",
    "phone2": "phone21u",
    "notes": "notesFf",
    "all_phones_from_home_page": null,
    "all_emails_from_home_page": null,
    "id": null
  }
]